{
  "openapi": "3.0.4",
  "info": {
    "title": "BudgetManagement.APIService",
    "version": "1.0"
  },
  "paths": {
    "/api/accounts": {
      "get": {
        "tags": [
          "Account"
        ],
        "responses": {
          "200": {
            "description": "OK"
          }
        }
      },
      "post": {
        "tags": [
          "Account"
        ],
        "requestBody": {
          "content": {
            "application/json": {
              "schema": {
                "$ref": "#/components/schemas/CreateAccountDto"
              }
            },
            "text/json": {
              "schema": {
                "$ref": "#/components/schemas/CreateAccountDto"
              }
            },
            "application/*+json": {
              "schema": {
                "$ref": "#/components/schemas/CreateAccountDto"
              }
            }
          }
        },
        "responses": {
          "200": {
            "description": "OK"
          }
        }
      }
    },
    "/api/accounts/type/{typeId}": {
      "get": {
        "tags": [
          "Account"
        ],
        "parameters": [
          {
            "name": "typeId",
            "in": "path",
            "required": true,
            "schema": {
              "type": "integer",
              "format": "int32"
            }
          }
        ],
        "responses": {
          "200": {
            "description": "OK"
          }
        }
      }
    },
    "/api/accounts/{id}": {
      "get": {
        "tags": [
          "Account"
        ],
        "parameters": [
          {
            "name": "id",
            "in": "path",
            "required": true,
            "schema": {
              "type": "integer",
              "format": "int32"
            }
          }
        ],
        "responses": {
          "200": {
            "description": "OK"
          }
        }
      },
      "put": {
        "tags": [
          "Account"
        ],
        "parameters": [
          {
            "name": "id",
            "in": "path",
            "required": true,
            "schema": {
              "type": "integer",
              "format": "int32"
            }
          }
        ],
        "requestBody": {
          "content": {
            "application/json": {
              "schema": {
                "$ref": "#/components/schemas/UpdateAccountDto"
              }
            },
            "text/json": {
              "schema": {
                "$ref": "#/components/schemas/UpdateAccountDto"
              }
            },
            "application/*+json": {
              "schema": {
                "$ref": "#/components/schemas/UpdateAccountDto"
              }
            }
          }
        },
        "responses": {
          "200": {
            "description": "OK"
          }
        }
      },
      "delete": {
        "tags": [
          "Account"
        ],
        "parameters": [
          {
            "name": "id",
            "in": "path",
            "required": true,
            "schema": {
              "type": "integer",
              "format": "int32"
            }
          }
        ],
        "responses": {
          "200": {
            "description": "OK"
          }
        }
      }
    },
    "/api/accounts/wallet-summary": {
      "get": {
        "tags": [
          "Account"
        ],
        "responses": {
          "200": {
            "description": "OK"
          }
        }
      }
    },
    "/api/budgets/expense": {
      "get": {
        "tags": [
          "Budget"
        ],
        "responses": {
          "200": {
            "description": "OK"
          }
        }
      },
      "post": {
        "tags": [
          "Budget"
        ],
        "requestBody": {
          "content": {
            "application/json": {
              "schema": {
                "$ref": "#/components/schemas/CreateBudgetDto"
              }
            },
            "text/json": {
              "schema": {
                "$ref": "#/components/schemas/CreateBudgetDto"
              }
            },
            "application/*+json": {
              "schema": {
                "$ref": "#/components/schemas/CreateBudgetDto"
              }
            }
          }
        },
        "responses": {
          "200": {
            "description": "OK"
          }
        }
      }
    },
    "/api/budgets/expense/{id}": {
      "get": {
        "tags": [
          "Budget"
        ],
        "parameters": [
          {
            "name": "id",
            "in": "path",
            "required": true,
            "schema": {
              "type": "integer",
              "format": "int32"
            }
          }
        ],
        "responses": {
          "200": {
            "description": "OK"
          }
        }
      },
      "put": {
        "tags": [
          "Budget"
        ],
        "parameters": [
          {
            "name": "id",
            "in": "path",
            "required": true,
            "schema": {
              "type": "integer",
              "format": "int32"
            }
          }
        ],
        "requestBody": {
          "content": {
            "application/json": {
              "schema": {
                "$ref": "#/components/schemas/UpdateBudgetDto"
              }
            },
            "text/json": {
              "schema": {
                "$ref": "#/components/schemas/UpdateBudgetDto"
              }
            },
            "application/*+json": {
              "schema": {
                "$ref": "#/components/schemas/UpdateBudgetDto"
              }
            }
          }
        },
        "responses": {
          "200": {
            "description": "OK"
          }
        }
      }
    },
    "/api/budgets/{id}": {
      "delete": {
        "tags": [
          "Budget"
        ],
        "parameters": [
          {
            "name": "id",
            "in": "path",
            "required": true,
            "schema": {
              "type": "integer",
              "format": "int32"
            }
          }
        ],
        "responses": {
          "200": {
            "description": "OK"
          }
        }
      }
    },
    "/api/budgets/savings": {
      "get": {
        "tags": [
          "Budget"
        ],
        "responses": {
          "200": {
            "description": "OK"
          }
        }
      },
      "post": {
        "tags": [
          "Budget"
        ],
        "requestBody": {
          "content": {
            "application/json": {
              "schema": {
                "$ref": "#/components/schemas/CreateSavingsGoalDto"
              }
            },
            "text/json": {
              "schema": {
                "$ref": "#/components/schemas/CreateSavingsGoalDto"
              }
            },
            "application/*+json": {
              "schema": {
                "$ref": "#/components/schemas/CreateSavingsGoalDto"
              }
            }
          }
        },
        "responses": {
          "200": {
            "description": "OK"
          }
        }
      }
    },
    "/api/budgets/savings/{id}": {
      "get": {
        "tags": [
          "Budget"
        ],
        "parameters": [
          {
            "name": "id",
            "in": "path",
            "required": true,
            "schema": {
              "type": "integer",
              "format": "int32"
            }
          }
        ],
        "responses": {
          "200": {
            "description": "OK"
          }
        }
      },
      "put": {
        "tags": [
          "Budget"
        ],
        "parameters": [
          {
            "name": "id",
            "in": "path",
            "required": true,
            "schema": {
              "type": "integer",
              "format": "int32"
            }
          }
        ],
        "requestBody": {
          "content": {
            "application/json": {
              "schema": {
                "$ref": "#/components/schemas/UpdateSavingsGoalDto"
              }
            },
            "text/json": {
              "schema": {
                "$ref": "#/components/schemas/UpdateSavingsGoalDto"
              }
            },
            "application/*+json": {
              "schema": {
                "$ref": "#/components/schemas/UpdateSavingsGoalDto"
              }
            }
          }
        },
        "responses": {
          "200": {
            "description": "OK"
          }
        }
      }
    },
    "/api/dashboard": {
      "get": {
        "tags": [
          "Dashboard"
        ],
        "responses": {
          "200": {
            "description": "OK"
          }
        }
      }
    },
    "/api/dashboard/recent": {
      "get": {
        "tags": [
          "Dashboard"
        ],
        "parameters": [
          {
            "name": "count",
            "in": "query",
            "schema": {
              "type": "integer",
              "format": "int32",
              "default": 5
            }
          }
        ],
        "responses": {
          "200": {
            "description": "OK"
          }
        }
      }
    },
    "/api/dashboard/spending": {
      "get": {
        "tags": [
          "Dashboard"
        ],
        "parameters": [
          {
            "name": "from",
            "in": "query",
            "schema": {
              "type": "string",
              "format": "date-time"
            }
          },
          {
            "name": "to",
            "in": "query",
            "schema": {
              "type": "string",
              "format": "date-time"
            }
          }
        ],
        "responses": {
          "200": {
            "description": "OK"
          }
        }
      }
    },
    "/api/dashboard/trend": {
      "get": {
        "tags": [
          "Dashboard"
        ],
        "parameters": [
          {
            "name": "months",
            "in": "query",
            "schema": {
              "type": "integer",
              "format": "int32",
              "default": 6
            }
          }
        ],
        "responses": {
          "200": {
            "description": "OK"
          }
        }
      }
    },
    "/api/recurring": {
      "get": {
        "tags": [
          "Recurring"
        ],
        "responses": {
          "200": {
            "description": "OK"
          }
        }
      },
      "post": {
        "tags": [
          "Recurring"
        ],
        "requestBody": {
          "content": {
            "application/json": {
              "schema": {
                "$ref": "#/components/schemas/CreateRecurringDto"
              }
            },
            "text/json": {
              "schema": {
                "$ref": "#/components/schemas/CreateRecurringDto"
              }
            },
            "application/*+json": {
              "schema": {
                "$ref": "#/components/schemas/CreateRecurringDto"
              }
            }
          }
        },
        "responses": {
          "200": {
            "description": "OK"
          }
        }
      }
    },
    "/api/recurring/{id}": {
      "get": {
        "tags": [
          "Recurring"
        ],
        "parameters": [
          {
            "name": "id",
            "in": "path",
            "required": true,
            "schema": {
              "type": "integer",
              "format": "int32"
            }
          }
        ],
        "responses": {
          "200": {
            "description": "OK"
          }
        }
      },
      "put": {
        "tags": [
          "Recurring"
        ],
        "parameters": [
          {
            "name": "id",
            "in": "path",
            "required": true,
            "schema": {
              "type": "integer",
              "format": "int32"
            }
          }
        ],
        "requestBody": {
          "content": {
            "application/json": {
              "schema": {
                "$ref": "#/components/schemas/UpdateRecurringDto"
              }
            },
            "text/json": {
              "schema": {
                "$ref": "#/components/schemas/UpdateRecurringDto"
              }
            },
            "application/*+json": {
              "schema": {
                "$ref": "#/components/schemas/UpdateRecurringDto"
              }
            }
          }
        },
        "responses": {
          "200": {
            "description": "OK"
          }
        }
      },
      "delete": {
        "tags": [
          "Recurring"
        ],
        "parameters": [
          {
            "name": "id",
            "in": "path",
            "required": true,
            "schema": {
              "type": "integer",
              "format": "int32"
            }
          }
        ],
        "responses": {
          "200": {
            "description": "OK"
          }
        }
      }
    },
    "/api/transactions": {
      "get": {
        "tags": [
          "Transaction"
        ],
        "parameters": [
          {
            "name": "page",
            "in": "query",
            "schema": {
              "type": "integer",
              "format": "int32",
              "default": 1
            }
          },
          {
            "name": "pageSize",
            "in": "query",
            "schema": {
              "type": "integer",
              "format": "int32",
              "default": 20
            }
          }
        ],
        "responses": {
          "200": {
            "description": "OK"
          }
        }
      },
      "post": {
        "tags": [
          "Transaction"
        ],
        "requestBody": {
          "content": {
            "application/json": {
              "schema": {
                "$ref": "#/components/schemas/CreateTransactionDto"
              }
            },
            "text/json": {
              "schema": {
                "$ref": "#/components/schemas/CreateTransactionDto"
              }
            },
            "application/*+json": {
              "schema": {
                "$ref": "#/components/schemas/CreateTransactionDto"
              }
            }
          }
        },
        "responses": {
          "200": {
            "description": "OK"
          }
        }
      }
    },
    "/api/transactions/range": {
      "get": {
        "tags": [
          "Transaction"
        ],
        "parameters": [
          {
            "name": "from",
            "in": "query",
            "schema": {
              "type": "string",
              "format": "date-time"
            }
          },
          {
            "name": "to",
            "in": "query",
            "schema": {
              "type": "string",
              "format": "date-time"
            }
          }
        ],
        "responses": {
          "200": {
            "description": "OK"
          }
        }
      }
    },
    "/api/transactions/{id}": {
      "get": {
        "tags": [
          "Transaction"
        ],
        "parameters": [
          {
            "name": "id",
            "in": "path",
            "required": true,
            "schema": {
              "type": "integer",
              "format": "int32"
            }
          }
        ],
        "responses": {
          "200": {
            "description": "OK"
          }
        }
      },
      "put": {
        "tags": [
          "Transaction"
        ],
        "parameters": [
          {
            "name": "id",
            "in": "path",
            "required": true,
            "schema": {
              "type": "integer",
              "format": "int32"
            }
          }
        ],
        "requestBody": {
          "content": {
            "application/json": {
              "schema": {
                "$ref": "#/components/schemas/UpdateTransactionDto"
              }
            },
            "text/json": {
              "schema": {
                "$ref": "#/components/schemas/UpdateTransactionDto"
              }
            },
            "application/*+json": {
              "schema": {
                "$ref": "#/components/schemas/UpdateTransactionDto"
              }
            }
          }
        },
        "responses": {
          "200": {
            "description": "OK"
          }
        }
      },
      "delete": {
        "tags": [
          "Transaction"
        ],
        "parameters": [
          {
            "name": "id",
            "in": "path",
            "required": true,
            "schema": {
              "type": "integer",
              "format": "int32"
            }
          }
        ],
        "responses": {
          "200": {
            "description": "OK"
          }
        }
      }
    },
    "/api/transactions/cashflow": {
      "get": {
        "tags": [
          "Transaction"
        ],
        "parameters": [
          {
            "name": "from",
            "in": "query",
            "schema": {
              "type": "string",
              "format": "date-time"
            }
          },
          {
            "name": "to",
            "in": "query",
            "schema": {
              "type": "string",
              "format": "date-time"
            }
          }
        ],
        "responses": {
          "200": {
            "description": "OK"
          }
        }
      }
    }
  },
  "components": {
    "schemas": {
      "CreateAccountDto": {
        "type": "object",
        "properties": {
          "typeId": {
            "type": "integer",
            "format": "int32"
          },
          "name": {
            "type": "string",
            "nullable": true
          },
          "iconName": {
            "type": "string",
            "nullable": true
          },
          "color": {
            "type": "string",
            "nullable": true
          },
          "gradientFrom": {
            "type": "string",
            "nullable": true
          },
          "gradientTo": {
            "type": "string",
            "nullable": true
          },
          "balance": {
            "type": "number",
            "format": "double",
            "nullable": true
          },
          "cardNumber": {
            "type": "string",
            "nullable": true
          }
        },
        "additionalProperties": false
      },
      "CreateBudgetDto": {
        "type": "object",
        "properties": {
          "accountId": {
            "type": "integer",
            "format": "int32"
          },
          "title": {
            "type": "string",
            "nullable": true
          },
          "targetAmount": {
            "type": "number",
            "format": "double"
          },
          "periodType": {
            "type": "string",
            "nullable": true
          },
          "startDate": {
            "type": "string",
            "format": "date-time"
          },
          "endDate": {
            "type": "string",
            "format": "date-time",
            "nullable": true
          },
          "iconName": {
            "type": "string",
            "nullable": true
          },
          "color": {
            "type": "string",
            "nullable": true
          }
        },
        "additionalProperties": false
      },
      "CreateRecurringDto": {
        "type": "object",
        "properties": {
          "debitAccountId": {
            "type": "integer",
            "format": "int32"
          },
          "creditAccountId": {
            "type": "integer",
            "format": "int32"
          },
          "amount": {
            "type": "number",
            "format": "double"
          },
          "title": {
            "type": "string",
            "nullable": true
          },
          "description": {
            "type": "string",
            "nullable": true
          },
          "frequency": {
            "type": "string",
            "nullable": true
          },
          "intervalValue": {
            "type": "integer",
            "format": "int32",
            "nullable": true
          },
          "nextRunDate": {
            "type": "string",
            "format": "date-time"
          }
        },
        "additionalProperties": false
      },
      "CreateSavingsGoalDto": {
        "type": "object",
        "properties": {
          "accountId": {
            "type": "integer",
            "format": "int32"
          },
          "title": {
            "type": "string",
            "nullable": true
          },
          "targetAmount": {
            "type": "number",
            "format": "double"
          },
          "initialAmount": {
            "type": "number",
            "format": "double",
            "nullable": true
          },
          "monthlyContribution": {
            "type": "number",
            "format": "double",
            "nullable": true
          },
          "deadline": {
            "type": "string",
            "nullable": true
          },
          "iconName": {
            "type": "string",
            "nullable": true
          },
          "color": {
            "type": "string",
            "nullable": true
          }
        },
        "additionalProperties": false
      },
      "CreateTransactionDto": {
        "type": "object",
        "properties": {
          "debitAccountId": {
            "type": "integer",
            "format": "int32"
          },
          "creditAccountId": {
            "type": "integer",
            "format": "int32"
          },
          "amount": {
            "type": "number",
            "format": "double"
          },
          "description": {
            "type": "string",
            "nullable": true
          },
          "transactionDate": {
            "type": "string",
            "format": "date-time",
            "nullable": true
          },
          "incomeCategoryName": {
            "type": "string",
            "nullable": true
          }
        },
        "additionalProperties": false
      },
      "UpdateAccountDto": {
        "type": "object",
        "properties": {
          "name": {
            "type": "string",
            "nullable": true
          },
          "iconName": {
            "type": "string",
            "nullable": true
          },
          "color": {
            "type": "string",
            "nullable": true
          },
          "gradientFrom": {
            "type": "string",
            "nullable": true
          },
          "gradientTo": {
            "type": "string",
            "nullable": true
          },
          "cardNumber": {
            "type": "string",
            "nullable": true
          },
          "isActive": {
            "type": "boolean",
            "nullable": true
          }
        },
        "additionalProperties": false
      },
      "UpdateBudgetDto": {
        "type": "object",
        "properties": {
          "title": {
            "type": "string",
            "nullable": true
          },
          "targetAmount": {
            "type": "number",
            "format": "double",
            "nullable": true
          },
          "periodType": {
            "type": "string",
            "nullable": true
          },
          "startDate": {
            "type": "string",
            "format": "date-time",
            "nullable": true
          },
          "endDate": {
            "type": "string",
            "format": "date-time",
            "nullable": true
          },
          "iconName": {
            "type": "string",
            "nullable": true
          },
          "color": {
            "type": "string",
            "nullable": true
          },
          "isActive": {
            "type": "boolean",
            "nullable": true
          }
        },
        "additionalProperties": false
      },
      "UpdateRecurringDto": {
        "type": "object",
        "properties": {
          "title": {
            "type": "string",
            "nullable": true
          },
          "description": {
            "type": "string",
            "nullable": true
          },
          "amount": {
            "type": "number",
            "format": "double",
            "nullable": true
          },
          "frequency": {
            "type": "string",
            "nullable": true
          },
          "intervalValue": {
            "type": "integer",
            "format": "int32",
            "nullable": true
          },
          "nextRunDate": {
            "type": "string",
            "format": "date-time",
            "nullable": true
          },
          "isActive": {
            "type": "boolean",
            "nullable": true
          }
        },
        "additionalProperties": false
      },
      "UpdateSavingsGoalDto": {
        "type": "object",
        "properties": {
          "title": {
            "type": "string",
            "nullable": true
          },
          "targetAmount": {
            "type": "number",
            "format": "double",
            "nullable": true
          },
          "monthlyContribution": {
            "type": "number",
            "format": "double",
            "nullable": true
          },
          "deadline": {
            "type": "string",
            "nullable": true
          },
          "iconName": {
            "type": "string",
            "nullable": true
          },
          "color": {
            "type": "string",
            "nullable": true
          },
          "isActive": {
            "type": "boolean",
            "nullable": true
          }
        },
        "additionalProperties": false
      },
      "UpdateTransactionDto": {
        "type": "object",
        "properties": {
          "description": {
            "type": "string",
            "nullable": true
          },
          "transactionDate": {
            "type": "string",
            "format": "date-time",
            "nullable": true
          }
        },
        "additionalProperties": false
      }
    }
  },
  "tags": [
    {
      "name": "Account"
    },
    {
      "name": "Budget"
    },
    {
      "name": "Dashboard"
    },
    {
      "name": "Recurring"
    },
    {
      "name": "Transaction"
    }
  ]
}